pytest_order_modify.py
setup.py
pytest_order_modify.egg-info/PKG-INFO
pytest_order_modify.egg-info/SOURCES.txt
pytest_order_modify.egg-info/dependency_links.txt
pytest_order_modify.egg-info/entry_points.txt
pytest_order_modify.egg-info/top_level.txt
test/__init__.py
test/conftest.py
test/test_examples/__init__.py
test/test_examples/test_example_1.py
test/test_examples/test_example_2.py
test/test_examples/test_example_3.py
test/test_files/__init__.py
test/test_files/test_file_1.py
test/test_files/test_file_2.py
test/test_files/test_file_3.py