Metadata-Version: 1.2
Name: pytest-order-modify
Version: 1.0
Summary: 新增run_marker 来自定义用例的执行顺序
Home-page: https://github.com/Jakilo1996/PytestTestOrderModify
Author: Jakilo
License: UNKNOWN
Platform: UNKNOWN
Classifier: Framework :: Pytest
Requires-Python:  >=3
